qecsim/__init__.py
qecsim/__main__.py
qecsim/app.py
qecsim/cli.py
qecsim/error.py
qecsim/model.py
qecsim/paulitools.py
qecsim/util.py
qecsim/graphtools/__init__.py
qecsim/graphtools/blossom5.py
qecsim/models/__init__.py
qecsim/models/basic.py
qecsim/models/color/__init__.py
qecsim/models/color/_color666code.py
qecsim/models/color/_color666mpsdecoder.py
qecsim/models/color/_color666pauli.py
qecsim/models/generic/__init__.py
qecsim/models/generic/_biasederrormodel.py
qecsim/models/generic/_fileerrormodel.py
qecsim/models/generic/_naivedecoder.py
qecsim/models/generic/_simpleerrormodel.py
qecsim/models/generic/_sliceerrormodel.py
qecsim/models/planar/__init__.py
qecsim/models/planar/_planarcmwpmdecoder.py
qecsim/models/planar/_planarcode.py
qecsim/models/planar/_planarmpsdecoder.py
qecsim/models/planar/_planarmwpmdecoder.py
qecsim/models/planar/_planarpauli.py
qecsim/models/planar/_planarrmpsdecoder.py
qecsim/models/planar/_planarydecoder.py
qecsim/models/rotatedplanar/__init__.py
qecsim/models/rotatedplanar/_rotatedplanarcode.py
qecsim/models/rotatedplanar/_rotatedplanarmpsdecoder.py
qecsim/models/rotatedplanar/_rotatedplanarpauli.py
qecsim/models/rotatedplanar/_rotatedplanarrmpsdecoder.py
qecsim/models/rotatedplanar/_rotatedplanarsmwpmdecoder.py
qecsim/models/rotatedtoric/__init__.py
qecsim/models/rotatedtoric/_rotatedtoriccode.py
qecsim/models/rotatedtoric/_rotatedtoricpauli.py
qecsim/models/rotatedtoric/_rotatedtoricsmwpmdecoder.py
qecsim/models/toric/__init__.py
qecsim/models/toric/_toriccode.py
qecsim/models/toric/_toricmwpmdecoder.py
qecsim/models/toric/_toricpauli.py
qecsim/tensortools/__init__.py
qecsim/tensortools/mps.py
qecsim/tensortools/mps2d.py
qecsim/tensortools/tsr.py
qecsim-1.0b9.dist-info/LICENSE
qecsim-1.0b9.dist-info/METADATA
qecsim-1.0b9.dist-info/WHEEL
qecsim-1.0b9.dist-info/entry_points.txt
qecsim-1.0b9.dist-info/top_level.txt
qecsim-1.0b9.dist-info/RECORD
