Metadata-Version: 2.1
Name: qecsim
Version: 1.0b9
Summary: Quantum error correction simulator
Home-page: https://github.com/qecsim/qecsim
Author: David K. Tuckett
Author-email: qecsim@gmail.com
License: BSD 3-Clause License
Project-URL: Source Code, https://github.com/qecsim/qecsim
Project-URL: Documentation, https://qecsim.github.io/
Project-URL: Issue tracker, https://github.com/qecsim/qecsim/issues
Platform: UNKNOWN
Classifier: Development Status :: 4 - Beta
Classifier: Intended Audience :: Science/Research
Classifier: Topic :: Scientific/Engineering
Classifier: Topic :: Scientific/Engineering :: Physics
Classifier: Operating System :: OS Independent
Classifier: Programming Language :: Python
Classifier: Programming Language :: Python :: 3
Classifier: License :: OSI Approved :: BSD License
Requires-Python: >=3.5
Requires-Dist: click (>=7)
Requires-Dist: numpy (>=1.17)
Requires-Dist: scipy (>=1.3)
Requires-Dist: networkx (>=2.1)
Requires-Dist: mpmath (>=1)
Provides-Extra: dev
Requires-Dist: tox ; extra == 'dev'
Requires-Dist: pytest ; extra == 'dev'
